plugin.cmake
setup.py
demo/Dockerfile
demo/demo.json
demo/run.sh
devops/.gitignore
devops/README.rst
devops/Vagrantfile
devops/playbooks/requirements.yml
devops/playbooks/site.yml
devops/playbooks/post-tasks/girder.yml
girder_item_tasks/__init__.py
girder_item_tasks/celery_tasks.py
girder_item_tasks/cli_parser.py
girder_item_tasks/constants.py
girder_item_tasks/json_tasks.py
girder_item_tasks/rest.py
girder_item_tasks/slicer_cli_tasks.py
girder_item_tasks.egg-info/PKG-INFO
girder_item_tasks.egg-info/SOURCES.txt
girder_item_tasks.egg-info/dependency_links.txt
girder_item_tasks.egg-info/entry_points.txt
girder_item_tasks.egg-info/not-zip-safe
girder_item_tasks.egg-info/requires.txt
girder_item_tasks.egg-info/top_level.txt
girder_item_tasks/web_client/index.js
girder_item_tasks/web_client/main.js
girder_item_tasks/web_client/package.json
girder_item_tasks/web_client/routes.js
girder_item_tasks/web_client/collections/ItemTaskCollection.js
girder_item_tasks/web_client/collections/WidgetCollection.js
girder_item_tasks/web_client/collections/index.js
girder_item_tasks/web_client/extra/widget_demo.json
girder_item_tasks/web_client/extra/bootstrap-colorpicker/alpha-horizontal.png
girder_item_tasks/web_client/extra/bootstrap-colorpicker/alpha.png
girder_item_tasks/web_client/extra/bootstrap-colorpicker/hue-horizontal.png
girder_item_tasks/web_client/extra/bootstrap-colorpicker/hue.png
girder_item_tasks/web_client/extra/bootstrap-colorpicker/saturation.png
girder_item_tasks/web_client/models/WidgetModel.js
girder_item_tasks/web_client/models/index.js
girder_item_tasks/web_client/stylesheets/configureTasks.styl
girder_item_tasks/web_client/stylesheets/controlWidget.styl
girder_item_tasks/web_client/stylesheets/controlsPanel.styl
girder_item_tasks/web_client/stylesheets/jobDetails.styl
girder_item_tasks/web_client/stylesheets/paginateTasksWidget.styl
girder_item_tasks/web_client/stylesheets/panel.styl
girder_item_tasks/web_client/stylesheets/selectTaskWidget.styl
girder_item_tasks/web_client/stylesheets/taskRun.styl
girder_item_tasks/web_client/templates/booleanWidget.pug
girder_item_tasks/web_client/templates/colorWidget.pug
girder_item_tasks/web_client/templates/configureCeleryTasks.pug
girder_item_tasks/web_client/templates/configureJsonTasks.pug
